frappuccino/__init__.py
frappuccino/__main__.py
frappuccino/astinit.py
frappuccino/logging.py
frappuccino/visitor.py
frappuccino/tests/IPython-7.14.0.json
frappuccino/tests/IPython-8.0.0.dev.json
frappuccino/tests/__init__.py
frappuccino/tests/new.py
frappuccino/tests/old.json
frappuccino/tests/old.py
frappuccino/tests/test_all.py
frappuccino/tests/test_basic.py
frappuccino-0.0.8.dist-info/entry_points.txt
frappuccino-0.0.8.dist-info/LICENSE
frappuccino-0.0.8.dist-info/WHEEL
frappuccino-0.0.8.dist-info/METADATA
frappuccino-0.0.8.dist-info/RECORD
